i_saas_utils/__init__.py
i_saas_utils/ansible/__init__.py
i_saas_utils/ansible/ansibl.py
i_saas_utils/git/__init__.py
i_saas_utils/git/git.py
i_saas_utils/git/git_project.py
i_saas_utils/git/git_repo.py
i_saas_utils/k8s/__init__.py
i_saas_utils/k8s/kube.py
i_saas_utils/saas/__init__.py
i_saas_utils/saas/saas.py
i_saas_utils/templates/__init__.py
i_saas_utils/templates/render.py
i_saas_utils/types/__init__.py
i_saas_utils-0.1.10.dist-info/METADATA
i_saas_utils-0.1.10.dist-info/WHEEL
i_saas_utils-0.1.10.dist-info/RECORD
