Metadata-Version: 2.1
Name: i-saas-utils
Version: 0.1.10
Summary: 
Author: Fedorov Stepan
Author-email: fedorov.stepan2@wb.ru
Requires-Python: >=3.11,<4.0
Classifier: Programming Language :: Python :: 3
Classifier: Programming Language :: Python :: 3.11
Requires-Dist: dnspython (>=2.4.1,<3.0.0)
Requires-Dist: gitpython (>=3.1.32,<4.0.0)
Requires-Dist: jinja2 (>=3.1.2,<4.0.0)
Requires-Dist: kubernetes (>=27.2.0,<28.0.0)
Requires-Dist: python-gitlab (>=3.15.0,<4.0.0)
